tmc_uart/__init__.py
tmc_uart/tmc5160_reg.py
tmc_uart/tmc_uart.py
tmc_uart/scripts/__init__.py
tmc_uart/scripts/cli.py
tmc_uart-0.1.3.dist-info/LICENSE
tmc_uart-0.1.3.dist-info/METADATA
tmc_uart-0.1.3.dist-info/WHEEL
tmc_uart-0.1.3.dist-info/top_level.txt
tmc_uart-0.1.3.dist-info/RECORD
