Metadata-Version: 2.1
Name: tmc-uart
Version: 0.1.3
Summary: Read/Write to Trinamic motion controller TMC5160 via the uart interface
Home-page: UNKNOWN
Author: Steve Troxel
Author-email: troxel@perlworks.com
License: MIT
Keywords: tmc5160 trinamic
Platform: UNKNOWN
Requires-Dist: pySerial
